hookedin/__init__.py
hookedin/hook_manager.py
hookedin/py.typed
hookedin/reducers.py
hookedin-1.0.0.dist-info/METADATA
hookedin-1.0.0.dist-info/WHEEL
hookedin-1.0.0.dist-info/licenses/LICENSE
hookedin-1.0.0.dist-info/RECORD
