Metadata-Version: 2.4
Name: hookedin
Version: 1.0.0
Summary: Lightweight async-friendly hook/plug-in manager with tags, priorities, and reducers.
Project-URL: Homepage, https://github.com/Kmdjr/hookedin
Project-URL: Issues, https://github.com/Kmdjr/hookedin/issues
Author-email: Kevin d'Anunciacao <kmdjr.dev@gmail.com>
License: MIT License
License-File: LICENSE
Keywords: asyncio,events,hooks,middleware,plugins
Classifier: License :: OSI Approved :: MIT License
Classifier: Operating System :: OS Independent
Classifier: Programming Language :: Python :: 3
Classifier: Programming Language :: Python :: 3 :: Only
Classifier: Programming Language :: Python :: 3.9
Classifier: Programming Language :: Python :: 3.10
Classifier: Programming Language :: Python :: 3.11
Classifier: Programming Language :: Python :: 3.12
Classifier: Topic :: Software Development :: Libraries
Classifier: Typing :: Typed
Requires-Python: >=3.9
Provides-Extra: dev
Requires-Dist: pytest-asyncio<0.24,>=0.23; extra == 'dev'
Requires-Dist: pytest>=8.0; extra == 'dev'
